fitsgeo/__init__.py
fitsgeo/cell.py
fitsgeo/const.py
fitsgeo/export.py
fitsgeo/material.py
fitsgeo/surface.py
fitsgeo/transform.py
fitsgeo/data/GDATABASE.dat
fitsgeo/data/PTABLE.dat
fitsgeo/data/PTDATABASE.dat
fitsgeo/data/SDATABASE.dat
FitsGeo-1.0.0.dist-info/LICENSE.txt
FitsGeo-1.0.0.dist-info/METADATA
FitsGeo-1.0.0.dist-info/WHEEL
FitsGeo-1.0.0.dist-info/top_level.txt
FitsGeo-1.0.0.dist-info/RECORD
