Metadata-Version: 2.1
Name: FitsGeo
Version: 1.0.0
Summary: FitsGeo: Python package for PHITS geometry development
Home-page: https://github.com/GordoNice/fitsgeo
Author: Ivan Gordeev
Author-email: gordeev@jinr.ru
License: UNKNOWN
Keywords: Python VPython PHITS geometry visualization development
Platform: UNKNOWN
Classifier: Programming Language :: Python :: 3.7
Classifier: Programming Language :: Python :: 3.8
Classifier: Development Status :: 5 - Production/Stable
Classifier: License :: OSI Approved :: MIT License
Classifier: Operating System :: OS Independent
Classifier: Topic :: Software Development :: Libraries :: Python Modules
Classifier: Topic :: Scientific/Engineering :: Physics
Classifier: Intended Audience :: Science/Research
Requires-Python: >=3.7
Requires-Dist: numpy (>=1.16.2)
Requires-Dist: pandas (>=0.25.1)
Requires-Dist: scipy (>=1.2.2)
Requires-Dist: vpython (>=7.6.1)
